dominosort/__init__.py
dominosort/metrics.py
dominosort/norms.py
dominosort/solver.py
dominosort/tests.py
dominosort/utils.py
dominosort-0.1.dist-info/DESCRIPTION.rst
dominosort-0.1.dist-info/METADATA
dominosort-0.1.dist-info/RECORD
dominosort-0.1.dist-info/WHEEL
dominosort-0.1.dist-info/metadata.json
dominosort-0.1.dist-info/top_level.txt
