Metadata-Version: 2.0
Name: dominosort
Version: 0.1
Summary: Sort sequences with respect to the similarity of consecutive items.
Home-page: https://gitlab.com/Dominik1123/dominosort
Author: Dominik Vilsmeier
Author-email: dominik.vilsmeier1123@gmail.com
License: BSD-3-Clause
Keywords: sort,sorting,algorithm
Platform: UNKNOWN
Classifier: Development Status :: 4 - Beta
Classifier: License :: OSI Approved :: BSD License
Classifier: Programming Language :: Python :: 3.4
Classifier: Programming Language :: Python :: 3.5
Classifier: Programming Language :: Python :: 3.6
Classifier: Topic :: Scientific/Engineering
Classifier: Topic :: Utilities
Requires-Dist: numpy (>=1.4.0)
Requires-Dist: scipy (>=0.15.0)
